{
  "annotations": {
    "list": [
      {
        "builtIn": 1,
        "datasource": {
          "type": "grafana",
          "uid": "-- Grafana --"
        },
        "enable": true,
        "hide": true,
        "iconColor": "rgba(0, 211, 255, 1)",
        "name": "Annotations & Alerts",
        "type": "dashboard"
      }
    ]
  },
  "editable": true,
  "fiscalYearStartMonth": 0,
  "graphTooltip": 0,
  "id": 7,
  "links": [],
  "panels": [
    {
      "datasource": {
        "type": "grafana-clickhouse-datasource",
        "uid": "P5DD39911892E6074"
      },
      "fieldConfig": {
        "defaults": {
          "color": {
            "mode": "palette-classic"
          },
          "custom": {
            "axisBorderShow": false,
            "axisCenteredZero": false,
            "axisColorMode": "text",
            "axisLabel": "",
            "axisPlacement": "auto",
            "barAlignment": 0,
            "barWidthFactor": 0.6,
            "drawStyle": "line",
            "fillOpacity": 10,
            "gradientMode": "none",
            "hideFrom": {
              "legend": false,
              "tooltip": false,
              "viz": false
            },
            "insertNulls": false,
            "lineInterpolation": "linear",
            "lineWidth": 1,
            "pointSize": 5,
            "scaleDistribution": {
              "type": "linear"
            },
            "showPoints": "never",
            "showValues": false,
            "spanNulls": false,
            "stacking": {
              "group": "A",
              "mode": "none"
            },
            "thresholdsStyle": {
              "mode": "off"
            }
          },
          "mappings": [],
          "min": 0,
          "thresholds": {
            "mode": "absolute",
            "steps": [
              {
                "color": "green",
                "value": 0
              },
              {
                "color": "red",
                "value": 80
              }
            ]
          },
          "unit": "bps"
        },
        "overrides": []
      },
      "gridPos": {
        "h": 10,
        "w": 24,
        "x": 0,
        "y": 0
      },
      "id": 1,
      "interval": "1m",
      "options": {
        "legend": {
          "calcs": ["min", "max", "p95", "mean", "lastNotNull"],
          "displayMode": "table",
          "placement": "bottom",
          "showLegend": true,
          "sortBy": "Max",
          "sortDesc": true
        },
        "tooltip": {
          "hideZeros": false,
          "mode": "multi",
          "sort": "none"
        }
      },
      "pluginVersion": "12.3.0",
      "targets": [
        {
          "datasource": {
            "type": "grafana-clickhouse-datasource",
            "uid": "P5DD39911892E6074"
          },
          "editorType": "sql",
          "format": 0,
          "meta": {
            "builderOptions": {
              "columns": [],
              "database": "",
              "limit": 1000,
              "mode": "list",
              "queryType": "table",
              "table": ""
            }
          },
          "pluginVersion": "4.11.4",
          "queryType": "timeseries",
          "rawSql": "SELECT\r\n  $__timeInterval(time_received) AS time,\r\n  proto,\r\n  sum(protoMap.bytes * 8 / $__interval_s) AS bps\r\nFROM flows.prefixes_proto_profile_1m\r\nARRAY JOIN protoMap.proto AS proto, protoMap.bytes\r\nWHERE $__timeFilter(time_received) AND prefix = ${prefix:sqlstring}\r\nGROUP BY proto, time\r\nORDER BY time",
          "refId": "A"
        }
      ],
      "title": "Traffic Rate",
      "type": "timeseries"
    },
    {
      "datasource": {
        "type": "grafana-clickhouse-datasource",
        "uid": "P5DD39911892E6074"
      },
      "fieldConfig": {
        "defaults": {
          "color": {
            "mode": "palette-classic"
          },
          "custom": {
            "axisBorderShow": false,
            "axisCenteredZero": false,
            "axisColorMode": "text",
            "axisLabel": "",
            "axisPlacement": "auto",
            "barAlignment": 0,
            "barWidthFactor": 0.6,
            "drawStyle": "line",
            "fillOpacity": 10,
            "gradientMode": "none",
            "hideFrom": {
              "legend": false,
              "tooltip": false,
              "viz": false
            },
            "insertNulls": false,
            "lineInterpolation": "linear",
            "lineWidth": 1,
            "pointSize": 5,
            "scaleDistribution": {
              "type": "linear"
            },
            "showPoints": "never",
            "showValues": false,
            "spanNulls": false,
            "stacking": {
              "group": "A",
              "mode": "none"
            },
            "thresholdsStyle": {
              "mode": "off"
            }
          },
          "mappings": [],
          "min": 0,
          "thresholds": {
            "mode": "absolute",
            "steps": [
              {
                "color": "green",
                "value": 0
              },
              {
                "color": "red",
                "value": 80
              }
            ]
          },
          "unit": "pps"
        },
        "overrides": []
      },
      "gridPos": {
        "h": 10,
        "w": 24,
        "x": 0,
        "y": 10
      },
      "id": 2,
      "interval": "1m",
      "options": {
        "legend": {
          "calcs": ["min", "max", "p95", "mean", "lastNotNull"],
          "displayMode": "table",
          "placement": "bottom",
          "showLegend": true,
          "sortBy": "Max",
          "sortDesc": true
        },
        "tooltip": {
          "hideZeros": false,
          "mode": "multi",
          "sort": "none"
        }
      },
      "pluginVersion": "12.3.0",
      "targets": [
        {
          "datasource": {
            "type": "grafana-clickhouse-datasource",
            "uid": "P5DD39911892E6074"
          },
          "editorType": "sql",
          "format": 0,
          "meta": {
            "builderOptions": {
              "columns": [],
              "database": "",
              "limit": 1000,
              "mode": "list",
              "queryType": "table",
              "table": ""
            }
          },
          "pluginVersion": "4.11.4",
          "queryType": "timeseries",
          "rawSql": "SELECT\r\n  $__timeInterval(time_received) AS time,\r\n  proto,\r\n  sum(protoMap.packets / $__interval_s) AS pps\r\nFROM flows.prefixes_proto_profile_1m\r\nARRAY JOIN protoMap.proto AS proto, protoMap.packets\r\nWHERE $__timeFilter(time_received) AND prefix = ${prefix:sqlstring}\r\nGROUP BY proto, time\r\nORDER BY time",
          "refId": "A"
        }
      ],
      "title": "Packets Rate",
      "type": "timeseries"
    }
  ],
  "preload": false,
  "refresh": "10s",
  "schemaVersion": 42,
  "tags": [],
  "templating": {
    "list": [
      {
        "allowCustomValue": false,
        "current": {
          "text": "169.150.235.0/24",
          "value": "169.150.235.0/24"
        },
        "datasource": {
          "type": "grafana-clickhouse-datasource",
          "uid": "P5DD39911892E6074"
        },
        "definition": "SELECT prefix FROM flows.prefixes",
        "label": "Prefix",
        "name": "prefix",
        "options": [],
        "query": "SELECT prefix FROM flows.prefixes",
        "refresh": 1,
        "regex": "",
        "type": "query"
      }
    ]
  },
  "time": {
    "from": "now-1h",
    "to": "now"
  },
  "timepicker": {},
  "timezone": "browser",
  "title": "Traffic for Prefix",
  "uid": "ads46q7",
  "version": 1
}
